rawdatx/__init__.py
rawdatx/_xml_parser.py
rawdatx/process_XML.py
rawdatx/read_TOA5.py
rawdatx-0.1.dist-info/DESCRIPTION.rst
rawdatx-0.1.dist-info/METADATA
rawdatx-0.1.dist-info/RECORD
rawdatx-0.1.dist-info/WHEEL
rawdatx-0.1.dist-info/metadata.json
rawdatx-0.1.dist-info/top_level.txt
