Metadata-Version: 2.0
Name: rawdatx
Version: 0.1
Summary: Generate Excel files from logger data files
Home-page: https://github.com/cpetrich/rawdatx
Author: Chris Petrich
Author-email: cpetrich@users.noreply.github.com
License: MIT
Keywords: file format
Platform: UNKNOWN
Classifier: Development Status :: 5 - Production/Stable
Classifier: Intended Audience :: Science/Research
Classifier: Natural Language :: English
Classifier: License :: OSI Approved :: MIT License
Classifier: Operating System :: OS Independent
Classifier: Programming Language :: Python
Classifier: Programming Language :: Python :: 2
Classifier: Programming Language :: Python :: 2.7
Classifier: Programming Language :: Python :: 3
Classifier: Programming Language :: Python :: 3.4
Classifier: Programming Language :: Python :: 3.5
Classifier: Programming Language :: Python :: Implementation :: CPython
Classifier: Topic :: Scientific/Engineering
